chembfn_webui/__init__.py
chembfn_webui/bin/app.py
chembfn_webui/bin/favicon.png
chembfn_webui/cache/cache_file_here.txt
chembfn_webui/cache/results.csv
chembfn_webui/lib/utilities.py
chembfn_webui/lib/version.py
chembfn_webui/model/base_model/place_base_model_here.txt
chembfn_webui/model/lora/place_lora_folder_here.txt
chembfn_webui/model/standalone_model/place_standalone_model_folder_here.txt
chembfn_webui/model/vocab/place_vocabulary_file_here.txt
chembfn_webui-2.1.8.dist-info/licenses/LICENSE
chembfn_webui-2.1.8.dist-info/METADATA
chembfn_webui-2.1.8.dist-info/WHEEL
chembfn_webui-2.1.8.dist-info/entry_points.txt
chembfn_webui-2.1.8.dist-info/top_level.txt
chembfn_webui-2.1.8.dist-info/RECORD
