Metadata-Version: 2.4
Name: chembfn_webui
Version: 2.1.8
Summary: WebUI for ChemBFN
Home-page: https://github.com/Augus1999/ChemBFN-WebUI
Author: Nianze A. Tao
Author-email: tao-nianze@hiroshima-u.ac.jp
License: AGPL-3.0-or-later
Project-URL: Source, https://github.com/Augus1999/ChemBFN-WebUI
Keywords: Chemistry,CLM,ChemBFN,WebUI
Classifier: Development Status :: 5 - Production/Stable
Classifier: Intended Audience :: Science/Research
Classifier: Natural Language :: English
Classifier: Programming Language :: Python :: 3
Classifier: Programming Language :: Python :: 3.11
Classifier: Programming Language :: Python :: 3.12
Classifier: Programming Language :: Python :: 3.13
Classifier: Programming Language :: Python :: 3.14
Classifier: Topic :: Scientific/Engineering :: Chemistry
Classifier: Topic :: Scientific/Engineering :: Artificial Intelligence
Requires-Python: >=3.11
License-File: LICENSE
Requires-Dist: bayesianflow_for_chem>=2.4.0
Requires-Dist: mol2chemfigPy3>=1.5.12
Requires-Dist: gradio<7.0.0,>=6.0.0
Requires-Dist: torch>=2.9.0
Requires-Dist: selfies>=2.2.0
Dynamic: author
Dynamic: author-email
Dynamic: classifier
Dynamic: description
Dynamic: description-content-type
Dynamic: home-page
Dynamic: keywords
Dynamic: license
Dynamic: license-file
Dynamic: project-url
Dynamic: requires-dist
Dynamic: requires-python
Dynamic: summary
